<manifest alg="2" build="2017.0.3.363" opt="false" iceEnabled="true" iceMarkupVersion="2" iceEnabledOptions="link,responsive,cachebuster,textStyling" exportTarget="other" domain="956901143@qq.com" resolutions="1x" timestamp="1500543332424">
  <folder name="css">
    <file name="site_global.css" crc="4285687840"/>
    <file name="index.css" crc="182335440" ref="index"/>
  </folder>
  <folder name="scripts">
    <file name="jquery-1.8.3.min.js" crc="209076791" ref="index"/>
    <file name="museutils.js" crc="46400467" ref="index"/>
    <file name="whatinput.js" crc="86476730" ref="index"/>
    <file name="museconfig.js" crc="436936948" ref="index"/>
    <file name="jquery.musepolyfill.bgsize.js" crc="532123423" ref="index"/>
    <file name="jquery.watch.js" crc="4178585335" ref="index"/>
    <file name="webpro.js" crc="4152390327" ref="index"/>
    <file name="musewpslideshow.js" crc="380562115" ref="index"/>
    <file name="jquery.museoverlay.js" crc="3986278607" ref="index"/>
    <file name="touchswipe.js" crc="4228958816" ref="index"/>
    <file name="jquery.scrolleffects.js" crc="410690402" ref="index"/>
    <file name="require.js" crc="85721165" ref="index"/>
  </folder>
  <folder name="images">
    <file name="cg-4wvwq3jkio2x5abwb8snkql8aagjrakj_t4ahbwk840.jpg" crc="4068916384" ref="index">
      <caption webpage="index" alt=""/>
    </file>
    <file name="blank.gif" crc="4208392903" ref="index"/>
    <file name="u113.png" crc="3856112144" ref="index"/>
    <file name="u113-r.png" crc="367609122" ref="index"/>
    <file name="u856.png" crc="4007185612" ref="index"/>
    <file name="u856-r.png" crc="3792160854" ref="index"/>
    <file name="u116.png" crc="3948874521" ref="index"/>
    <file name="u116-r.png" crc="4111343375" ref="index"/>
    <file name="u119.png" crc="3812213581" ref="index"/>
    <file name="u119-r.png" crc="66176473" ref="index"/>
    <file name="u122.png" crc="506911051" ref="index"/>
    <file name="u122-r.png" crc="507220465" ref="index"/>
    <file name="20160723162226_fzbfr.jpg" crc="4010911456" ref="index">
      <caption webpage="index" alt=""/>
    </file>
    <file name="u806-4.png" crc="4022300012" ref="index"/>
    <file name="u805-4.png" crc="4145715083" ref="index"/>
    <file name="20160324131049_2emurthumb700_0.jpg" crc="4064873149" ref="index">
      <caption webpage="index" alt=""/>
    </file>
    <file name="u835-4.png" crc="4022300012" ref="index"/>
    <file name="u834-4.png" crc="4145715083" ref="index"/>
    <file name="u404-4.png" crc="3910431688" ref="index"/>
    <file name="img_8856.jpg" crc="159232986" ref="index">
      <caption webpage="index" alt=""/>
    </file>
    <file name="img_8857.jpg" crc="456675713" ref="index">
      <caption webpage="index" alt=""/>
    </file>
    <file name="img_8858.jpg" crc="4239517796" ref="index">
      <caption webpage="index" alt=""/>
    </file>
    <file name="cg-4wvwq3rciogvfahau-sx3vh8aagjsqaaaaaadpur256.jpg" crc="80808634" ref="index">
      <caption webpage="index" alt=""/>
    </file>
    <file name="img_8938.jpg" crc="4133091845" ref="index">
      <caption webpage="index" alt=""/>
      <caption webpage="index" alt=""/>
    </file>
    <file name="img_8937.jpg" crc="4041249472" ref="index">
      <caption webpage="index" alt=""/>
      <caption webpage="index" alt=""/>
    </file>
    <file name="u419-4.png" crc="4177263149" ref="index"/>
    <file name="img_8936.jpg" crc="4087534589" ref="index">
      <caption webpage="index" alt=""/>
    </file>
    <file name="img_8941.jpg" crc="3870636673" ref="index">
      <caption webpage="index" alt=""/>
    </file>
    <file name="img_8940.jpg" crc="3973924841" ref="index">
      <caption webpage="index" alt=""/>
    </file>
    <file name="img_8939.jpg" crc="106859326" ref="index">
      <caption webpage="index" alt=""/>
    </file>
    <file name="u443-4.png" crc="4202932943" ref="index"/>
    <file name="0436540f1b676a57dcb8369769c11cac9bf22dc52500e-0mncfz_fw658.jpg" crc="4000517180" ref="index">
      <caption webpage="index" alt=""/>
    </file>
    <file name="u449-4.png" crc="49823994" ref="index"/>
    <file name="c50db516d7bca96317faba50c33c9dd07a5b30257043-4lfv5m_fw658.jpg" crc="4186587929" ref="index">
      <caption webpage="index" alt=""/>
    </file>
    <file name="u455-4.png" crc="4127271644" ref="index"/>
    <file name="70e6c98d46c5d87733f269e9dcc89856744516371d3cf-ric0xu_fw658.jpg" crc="4229145134" ref="index">
      <caption webpage="index" alt=""/>
    </file>
    <file name="u461-4.png" crc="233644939" ref="index"/>
    <file name="f3d1dd03cea8868eac4d4d2dafc8474b2ac28e9617123-0tnvzj_fw658.jpg" crc="330955739" ref="index">
      <caption webpage="index" alt=""/>
    </file>
    <file name="u476-4.png" crc="3889640545" ref="index"/>
    <file name="d016b71059f4602edd8085b59dbc2e9e22c7e5297c32-3vxays_fw658.jpg" crc="3844542069" ref="index">
      <caption webpage="index" alt=""/>
    </file>
    <file name="u470-4.png" crc="465516385" ref="index"/>
    <file name="8fb48027031e89af463ae1cf890058d4ceddb60f4e4e-7zf8yh_fw658.jpg" crc="4284804168" ref="index">
      <caption webpage="index" alt=""/>
    </file>
    <file name="u464-4.png" crc="527760856" ref="index"/>
    <file name="u862-7.png" crc="362358480" ref="index"/>
  </folder>
  <file name="index.html" crc="3772821567" seo="true" mt="1500470987232" redirect="true"/>
</manifest>
